shinnosuke/__init__.py
shinnosuke/models.py
shinnosuke/layers/Activation.py
shinnosuke/layers/Base.py
shinnosuke/layers/Convolution.py
shinnosuke/layers/Dropout.py
shinnosuke/layers/Embeddings.py
shinnosuke/layers/FC.py
shinnosuke/layers/Normalization.py
shinnosuke/layers/Recurrent.py
shinnosuke/layers/Wrappers.py
shinnosuke/layers/__init__.py
shinnosuke/utils/Activator.py
shinnosuke/utils/ConvCol.py
shinnosuke/utils/Initializers.py
shinnosuke/utils/MiniBatch.py
shinnosuke/utils/Objectives.py
shinnosuke/utils/Optimizers.py
shinnosuke/utils/Preprocess.py
shinnosuke/utils/Regularizers.py
shinnosuke/utils/__init__.py
shinnosuke-0.6.1.dist-info/LICENSE
shinnosuke-0.6.1.dist-info/METADATA
shinnosuke-0.6.1.dist-info/WHEEL
shinnosuke-0.6.1.dist-info/top_level.txt
shinnosuke-0.6.1.dist-info/RECORD
